public_invest_api/__init__.py
public_invest_api/endpoints.py
public_invest_api/public.py
public_invest_api-1.3.5.dist-info/licenses/LICENSE
public_invest_api-1.3.5.dist-info/METADATA
public_invest_api-1.3.5.dist-info/WHEEL
public_invest_api-1.3.5.dist-info/top_level.txt
public_invest_api-1.3.5.dist-info/RECORD
