Metadata-Version: 2.4
Name: public_invest_api
Version: 1.3.5
Summary: Unofficial Public.com Invest API written in Python Requests
Home-page: https://github.com/NelsonDane/public-invest-api
Author: Nelson Dane
License-File: LICENSE
Requires-Dist: requests>=2.23.0
Dynamic: author
Dynamic: description
Dynamic: description-content-type
Dynamic: home-page
Dynamic: license-file
Dynamic: requires-dist
Dynamic: summary
